setup.py
yandex_ci_parser/__init__.py
yandex_ci_parser/bar.py
yandex_ci_parser/errors.py
yandex_ci_parser/image.py
yandex_ci_parser/simple.py
yandex_ci_parser/util.py
yandex_ci_parser/yaca.py
yandex_ci_parser.egg-info/PKG-INFO
yandex_ci_parser.egg-info/SOURCES.txt
yandex_ci_parser.egg-info/dependency_links.txt
yandex_ci_parser.egg-info/top_level.txt