Metadata-Version: 1.1
Name: yandex-ci-parser
Version: 0.0.2
Summary: Fetch yandex ci
Home-page: https://github.com/KokocGroup/yandex-ci-parser
Author: UNKNOWN
Author-email: UNKNOWN
License: UNKNOWN
Download-URL: https://github.com/KokocGroup/yandex-ci-parser/tarball/v0.0.2
Platform: UNKNOWN
